equip/__init__.py
equip/instrument.py
equip/prog.py
equip/bytecode/__init__.py
equip/bytecode/code.py
equip/bytecode/decl.py
equip/bytecode/utils.py
equip/rewriter/__init__.py
equip/rewriter/merger.py
equip/rewriter/simple.py
equip/utils/__init__.py
equip/utils/files.py
equip/utils/log.py
equip/visitors/__init__.py
equip/visitors/bytecode.py
equip/visitors/classes.py
equip/visitors/methods.py
equip/visitors/modules.py
equip-0.1.dist-info/DESCRIPTION.rst
equip-0.1.dist-info/entry_points.txt
equip-0.1.dist-info/METADATA
equip-0.1.dist-info/metadata.json
equip-0.1.dist-info/RECORD
equip-0.1.dist-info/top_level.txt
equip-0.1.dist-info/WHEEL
