Metadata-Version: 2.0
Name: equip
Version: 0.1
Summary: Python bytecode instrumentation framework
Home-page: https://github.com/neuroo/equip
Author: Romain Gaucher
Author-email: r@rgaucher.info
License: APACHE
Keywords: bytecode injection instrumentation
Platform: UNKNOWN
Classifier: Development Status :: 1 - Planning
Classifier: Programming Language :: Python
